smc/__init__.py
smc/cli.py
smc/config.py
smc/controllers/__init__.py
smc/controllers/auto.py
smc/controllers/entity.py
smc/controllers/semantic_model.py
smc/controllers/table.py
smc/models/__init__.py
smc/models/base.py
smc/models/entity.py
smc/models/ontology.py
smc/models/project.py
smc/models/semantic_model.py
smc/models/table.py
smc/plugins/__init__.py
smc/plugins/wikidata.py
smc/restful.py
smc/webapp.py
smc/www/asset-manifest.json
smc/www/favicon.ico
smc/www/index.html
smc/www/logo192.png
smc/www/logo512.png
smc/www/manifest.json
smc/www/robots.txt
smc/www/static/css/2.7939ea52.chunk.css
smc/www/static/css/2.7939ea52.chunk.css.map
smc/www/static/css/main.8977ddd9.chunk.css
smc/www/static/css/main.8977ddd9.chunk.css.map
smc/www/static/js/2.706f5173.chunk.js
smc/www/static/js/2.706f5173.chunk.js.LICENSE.txt
smc/www/static/js/2.706f5173.chunk.js.map
smc/www/static/js/3.ad268873.chunk.js
smc/www/static/js/3.ad268873.chunk.js.map
smc/www/static/js/main.237d158d.chunk.js
smc/www/static/js/main.237d158d.chunk.js.map
smc/www/static/js/runtime-main.c08ddcc5.js
smc/www/static/js/runtime-main.c08ddcc5.js.map
smc/www/static/media/index.0073fa4c.less
smc/www/static/media/index.030309a0.less
smc/www/static/media/index.05af8560.less
smc/www/static/media/index.06976f3a.less
smc/www/static/media/index.08be011d.less
smc/www/static/media/index.12dfc422.less
smc/www/static/media/index.1402b635.less
smc/www/static/media/index.14f3efed.less
smc/www/static/media/index.19170906.less
smc/www/static/media/index.2e5a0a4e.less
smc/www/static/media/index.3745ed15.less
smc/www/static/media/index.3755abd3.less
smc/www/static/media/index.3a8f6637.less
smc/www/static/media/index.3bc07efa.less
smc/www/static/media/index.417e6e35.less
smc/www/static/media/index.41918f24.less
smc/www/static/media/index.4559f08d.less
smc/www/static/media/index.4e3ca355.less
smc/www/static/media/index.4ea79b6b.less
smc/www/static/media/index.4fc6f883.less
smc/www/static/media/index.5468db5c.less
sem_desc_curator-0.1.0.dist-info/entry_points.txt
sem_desc_curator-0.1.0.dist-info/WHEEL
sem_desc_curator-0.1.0.dist-info/METADATA
sem_desc_curator-0.1.0.dist-info/RECORD
