Metadata-Version: 2.1
Name: sem-desc-curator
Version: 0.1.0
Summary: UI for browsing/editing semantic descriptions
License: MIT
Author: Binh Vu
Author-email: binh@toan2.com
Requires-Python: >=3.8,<4.0
Classifier: License :: OSI Approved :: MIT License
Classifier: Programming Language :: Python :: 3
Classifier: Programming Language :: Python :: 3.8
Classifier: Programming Language :: Python :: 3.9
Requires-Dist: Flask (>=2.0.1,<3.0.0)
Requires-Dist: kgdata (>=1.2.3,<2.0.0)
Requires-Dist: peewee (>=3.14.4,<4.0.0)
Requires-Dist: python-dotenv (>=0.19.0,<0.20.0)
Requires-Dist: sem-desc (>=0.1.15,<0.2.0)
Requires-Dist: tornado (>=6.1,<7.0)
